oxmenu/__init__.py
oxmenu/main.py
oxmenu-0.0.3.dist-info/METADATA
oxmenu-0.0.3.dist-info/WHEEL
oxmenu-0.0.3.dist-info/top_level.txt
oxmenu-0.0.3.dist-info/RECORD
