Metadata-Version: 2.1
Name: oxmenu
Version: 0.0.3
Summary: A Handy Package to Create 3 Different types of Menus
Author: 0x68616469
Keywords: menu,arrow key,checkbox
Classifier: Development Status :: 4 - Beta
Classifier: Intended Audience :: Developers
Classifier: Programming Language :: Python :: 3
Classifier: Operating System :: Unix
Classifier: Operating System :: MacOS :: MacOS X
Requires-Dist: oxansi
